[{"category_display":"enable","category_flag":"n","category_list_url":"","category_url":"about.html","top_id":0,"category_short_title":"网站建设「一站式」服务商","category_type":"2","del":0,"leaf":0,"category_pinyin":"guanyuwomen","category_diy_url":"","category_sort":0,"category_img":"[{\"path\":\"/upload/images/banner.jpg\",\"name\":\"banner.jpg\",\"url\":\"/upload/images/banner.jpg\",\"status\":\"success\"}]","update_date":1625888101000,"category_descrip":"","create_by":"57","category_title":"关于我们","category_path":"/guanyuwomen","category_ico":"","category_keyword":"","id":1,"update_by":"57","create_date":1523438771000},{"category_display":"enable","category_flag":"n","category_list_url":"newslist.html","category_url":"news.html","top_id":0,"category_short_title":"NEWS","category_type":"1","del":0,"leaf":0,"category_pinyin":"xinwendongtai","category_diy_url":"","category_sort":0,"category_img":"[{\"path\":\"/upload/images/banner.jpg\",\"name\":\"banner.jpg\",\"url\":\"/upload/images/banner.jpg\",\"status\":\"success\"}]","update_date":1625896929000,"category_descrip":"","create_by":"57","category_title":"新闻动态","category_path":"/xinwendongtai","category_ico":"[{\"path\":\"/upload/images/jzchangshi.jpg\",\"name\":\"jzchangshi.jpg\",\"url\":\"/upload/images/jzchangshi.jpg\",\"status\":\"success\"}]","category_keyword":"","id":2,"update_by":"57","create_date":1523438806000},{"category_display":"enable","category_list_url":"newslist.html","category_url":"news.html","top_id":2,"category_short_title":"了解最新公司动态及行业资讯","category_type":"1","del":0,"leaf":1,"category_pinyin":"jianzhanchangshi","category_diy_url":"","category_sort":0,"category_img":"[{\"path\":\"/upload/images/banner.jpg\",\"name\":\"banner.jpg\",\"url\":\"/upload/images/banner.jpg\",\"status\":\"success\"}]","update_date":1625895393000,"category_descrip":"","create_by":"57","category_title":"建站常识","category_id":2,"category_path":"/xinwendongtai/jianzhanchangshi","category_ico":"[{\"path\":\"/upload/images/jzchangshi.jpg\",\"name\":\"jzchangshi.jpg\",\"url\":\"/upload/images/jzchangshi.jpg\",\"status\":\"success\"}]","category_keyword":"","id":3,"category_parent_ids":"2","update_by":"57","create_date":1523438825000},{"category_display":"enable","category_list_url":"newslist.html","category_url":"news.html","top_id":2,"category_short_title":"QUESTION","category_type":"1","del":0,"leaf":1,"category_pinyin":"changjianwenti","category_diy_url":"","category_sort":0,"category_img":"[{\"path\":\"/upload/images/banner.jpg\",\"name\":\"banner.jpg\",\"url\":\"/upload/images/banner.jpg\",\"status\":\"success\"}]","update_date":1625905785000,"category_descrip":"","create_by":"57","category_title":"常见问题","category_id":2,"category_path":"/xinwendongtai/changjianwenti","category_ico":"[{\"path\":\"/upload/images/jzchangshi.jpg\",\"name\":\"jzchangshi.jpg\",\"url\":\"/upload/images/jzchangshi.jpg\",\"status\":\"success\"}]","category_keyword":"","id":4,"category_parent_ids":"2","update_by":"57","create_date":1523438850000},{"category_display":"enable","category_flag":"n","category_list_url":"","category_url":"mb1.html","top_id":0,"category_short_title":"专业网站建设及开发服务，包括企业网站、品牌网站、电商网站......","category_type":"2","del":0,"leaf":0,"category_pinyin":"wangzhanjianshe","category_diy_url":"","category_sort":0,"category_img":"[{\"path\":\"/upload/images/banner.jpg\",\"name\":\"banner.jpg\",\"url\":\"/upload/images/banner.jpg\",\"status\":\"success\"}]","update_date":1629466476000,"category_descrip":"","create_by":"57","category_title":"网站建设","category_path":"/wangzhanjianshe","category_ico":"","category_keyword":"","id":5,"update_by":"57","create_date":1523438874000},{"category_display":"enable","category_list_url":"","category_url":"mb1.html","top_id":5,"category_short_title":"服务创造价值、存在造就未来","category_type":"2","del":0,"leaf":1,"category_pinyin":"mobanxingwangzhan","category_diy_url":"","category_sort":0,"category_img":"[{\"path\":\"/upload/images/banner.jpg\",\"name\":\"banner.jpg\",\"url\":\"/upload/images/banner.jpg\",\"status\":\"success\"}]","update_date":1625890366000,"category_descrip":"","create_by":"57","category_title":"模板型网站","category_id":5,"category_path":"/wangzhanjianshe/mobanxingwangzhan","category_ico":"","category_keyword":"","id":6,"category_parent_ids":"5","update_by":"57","create_date":1523438899000},{"category_display":"enable","category_list_url":"","category_url":"mb2.html","top_id":5,"category_short_title":"服务创造价值、存在造就未来","category_type":"2","del":0,"leaf":1,"category_pinyin":"biaozhunxingwangzhan","category_diy_url":"","category_sort":0,"category_img":"[{\"path\":\"/upload/images/banner.jpg\",\"name\":\"banner.jpg\",\"url\":\"/upload/images/banner.jpg\",\"status\":\"success\"}]","update_date":1625890401000,"category_descrip":"","create_by":"57","category_title":"标准型网站","category_id":5,"category_path":"/wangzhanjianshe/biaozhunxingwangzhan","category_ico":"","category_keyword":"","id":7,"category_parent_ids":"5","update_by":"57","create_date":1523438918000},{"category_display":"enable","category_flag":"n","category_list_url":"caselist.html","category_url":"case.html","top_id":0,"category_short_title":"专业技术团队，展示效果好，值得信赖，助力品牌成为行业标杆，发展新趋势......","category_type":"1","del":0,"leaf":0,"category_pinyin":"kehuanli","category_diy_url":"","category_sort":0,"category_img":"[{\"path\":\"/upload/images/banner.jpg\",\"name\":\"banner.jpg\",\"url\":\"/upload/images/banner.jpg\",\"status\":\"success\"}]","update_date":1625888101000,"category_descrip":"","create_by":"57","category_title":"客户案例","category_path":"/kehuanli","category_ico":"","category_keyword":"","id":8,"update_by":"57","create_date":1523438956000},{"category_display":"enable","category_flag":"n","category_list_url":"seolist.html","category_url":"seo.html","top_id":0,"category_short_title":"整站优化、百度SEO排名、广告投放搜狗、360搜索竞价排名。一条龙服务...","category_type":"1","del":0,"leaf":0,"category_pinyin":"paimingyouhua","category_diy_url":"","category_sort":0,"category_img":"[{\"path\":\"/upload/images/banner.jpg\",\"name\":\"banner.jpg\",\"url\":\"/upload/images/banner.jpg\",\"status\":\"success\"}]","update_date":1625925197000,"category_descrip":"","create_by":"57","category_title":"排名优化","category_path":"/paimingyouhua","category_ico":"","category_keyword":"","id":9,"update_by":"57","create_date":1523439002000},{"category_display":"enable","category_flag":"n","category_list_url":"shejilist.html","category_url":"sheji.html","top_id":0,"category_short_title":"专业企业品牌设计，专属定制LOGO,PPT,画册,海报等，让企业形象创造更高价值...","category_type":"1","del":0,"leaf":0,"category_pinyin":"pinpaisheji","category_diy_url":"","category_sort":0,"category_img":"[{\"path\":\"/upload/images/banner.jpg\",\"name\":\"banner.jpg\",\"url\":\"/upload/images/banner.jpg\",\"status\":\"success\"}]","update_date":1625923604000,"category_descrip":"","create_by":"57","category_title":"品牌设计","category_path":"/pinpaisheji","category_ico":"","category_keyword":"","id":10,"update_by":"57","create_date":1523439036000},{"category_display":"enable","category_flag":"n","category_list_url":"","category_url":"contact.html","top_id":0,"category_short_title":"能为您服务是我们的荣幸","category_type":"2","del":0,"leaf":0,"category_pinyin":"lianxiwomen","category_diy_url":"","category_sort":0,"category_img":"[{\"path\":\"/upload/images/banner.jpg\",\"name\":\"banner.jpg\",\"url\":\"/upload/images/banner.jpg\",\"status\":\"success\"}]","update_date":1625929420000,"category_descrip":"","create_by":"57","category_title":"联系我们","category_path":"/lianxiwomen","category_ico":"","category_keyword":"","id":11,"update_by":"57","create_date":1523439089000},{"category_display":"enable","category_list_url":"","category_url":"mb3.html","top_id":5,"category_short_title":"","category_type":"2","del":0,"leaf":1,"category_pinyin":"xiangyingshiwangzhan","category_diy_url":"","category_sort":0,"category_img":"[{\"path\":\"/upload/images/banner.jpg\",\"name\":\"banner.jpg\",\"url\":\"/upload/images/banner.jpg\",\"status\":\"success\"}]","update_date":1625890936000,"category_descrip":"","create_by":"57","category_title":"响应式网站","category_id":5,"category_path":"/wangzhanjianshe/xiangyingshiwangzhan","category_ico":"","category_keyword":"","id":13,"category_parent_ids":"5","update_by":"57","create_date":1625890936000},{"category_display":"enable","category_list_url":"","category_url":"mb4.html","top_id":5,"category_short_title":"","category_type":"2","del":0,"leaf":1,"category_pinyin":"jituanxingwangzhan","category_diy_url":"","category_sort":0,"category_img":"[{\"path\":\"/upload/images/banner.jpg\",\"name\":\"banner.jpg\",\"url\":\"/upload/images/banner.jpg\",\"status\":\"success\"}]","update_date":1625908730000,"category_descrip":"","create_by":"57","category_title":"集团型网站","category_id":5,"category_path":"/wangzhanjianshe/jituanxingwangzhan","category_ico":"","category_keyword":"","id":14,"category_parent_ids":"5","update_by":"57","create_date":1625890936000},{"category_display":"enable","category_list_url":"caselist.html","category_url":"case.html","top_id":8,"category_short_title":"","category_type":"1","del":0,"leaf":1,"category_pinyin":"qiyeguanwangjianshe","category_diy_url":"","category_sort":0,"category_img":"[{\"path\":\"/upload/images/banner.jpg\",\"name\":\"banner.jpg\",\"url\":\"/upload/images/banner.jpg\",\"status\":\"success\"}]","update_date":1625890983000,"category_descrip":"","create_by":"57","category_title":"企业官网建设","category_id":8,"category_path":"/kehuanli/qiyeguanwangjianshe","category_ico":"","category_keyword":"","id":15,"category_parent_ids":"8","update_by":"57","create_date":1625890983000},{"category_display":"enable","category_list_url":"caselist.html","category_url":"case.html","top_id":8,"category_short_title":"","category_type":"1","del":0,"leaf":1,"category_pinyin":"yingxiaoxingwangzhan","category_diy_url":"","category_sort":0,"category_img":"[{\"path\":\"/upload/images/banner.jpg\",\"name\":\"banner.jpg\",\"url\":\"/upload/images/banner.jpg\",\"status\":\"success\"}]","update_date":1625890983000,"category_descrip":"","create_by":"57","category_title":"营销型网站","category_id":8,"category_path":"/kehuanli/yingxiaoxingwangzhan","category_ico":"","category_keyword":"","id":16,"category_parent_ids":"8","update_by":"57","create_date":1625890983000},{"category_display":"enable","category_list_url":"caselist.html","category_url":"case.html","top_id":8,"category_short_title":"","category_type":"1","del":0,"leaf":1,"category_pinyin":"gaoduanwangzhananli","category_diy_url":"","category_sort":0,"category_img":"[{\"path\":\"/upload/images/banner.jpg\",\"name\":\"banner.jpg\",\"url\":\"/upload/images/banner.jpg\",\"status\":\"success\"}]","update_date":1625890983000,"category_descrip":"","create_by":"57","category_title":"高端网站案例","category_id":8,"category_path":"/kehuanli/gaoduanwangzhananli","category_ico":"","category_keyword":"","id":17,"category_parent_ids":"8","update_by":"57","create_date":1625890983000},{"category_display":"enable","category_list_url":"caselist.html","category_url":"case.html","top_id":8,"category_short_title":"","category_type":"1","del":0,"leaf":1,"category_pinyin":"xiangyingshiwangzhan","category_diy_url":"","category_sort":0,"category_img":"[{\"path\":\"/upload/images/banner.jpg\",\"name\":\"banner.jpg\",\"url\":\"/upload/images/banner.jpg\",\"status\":\"success\"}]","update_date":1625890983000,"category_descrip":"","create_by":"57","category_title":"响应式网站","category_id":8,"category_path":"/kehuanli/xiangyingshiwangzhan","category_ico":"","category_keyword":"","id":18,"category_parent_ids":"8","update_by":"57","create_date":1625890983000},{"category_display":"enable","category_list_url":"newslist.html","category_url":"news.html","top_id":2,"category_short_title":"","category_type":"1","del":0,"leaf":1,"category_pinyin":"paimingyouhua","category_diy_url":"","category_sort":0,"category_img":"[{\"path\":\"/upload/images/banner.jpg\",\"name\":\"banner.jpg\",\"url\":\"/upload/images/banner.jpg\",\"status\":\"success\"}]","update_date":1625895495000,"category_descrip":"","create_by":"57","category_title":"排名优化","category_id":2,"category_path":"/xinwendongtai/paimingyouhua","category_ico":"[{\"path\":\"/upload/images/jzchangshi.jpg\",\"name\":\"jzchangshi.jpg\",\"url\":\"/upload/images/jzchangshi.jpg\",\"status\":\"success\"}]","category_keyword":"","id":19,"category_parent_ids":"2","update_by":"57","create_date":1625895495000},{"category_display":"enable","category_list_url":"newslist.html","category_url":"news.html","top_id":2,"category_short_title":"客户签约是对我们最大的支持和鼓励，感谢签约的客户！","category_type":"1","del":0,"leaf":1,"category_pinyin":"qianyuedongtai","category_diy_url":"","category_sort":0,"category_img":"[{\"path\":\"/upload/images/banner.jpg\",\"name\":\"banner.jpg\",\"url\":\"/upload/images/banner.jpg\",\"status\":\"success\"}]","update_date":1625895495000,"category_descrip":"","create_by":"57","category_title":"签约动态","category_id":2,"category_path":"/xinwendongtai/qianyuedongtai","category_ico":"[{\"path\":\"/upload/images/jzchangshi.jpg\",\"name\":\"jzchangshi.jpg\",\"url\":\"/upload/images/jzchangshi.jpg\",\"status\":\"success\"}]","category_keyword":"","id":20,"category_parent_ids":"2","update_by":"57","create_date":1625895495000},{"category_display":"enable","category_list_url":"huolist.html","category_url":"huo.html","top_id":0,"category_short_title":"partners","category_type":"1","del":0,"leaf":1,"category_pinyin":"hezuodanwei","category_diy_url":"","category_sort":0,"category_img":"","update_date":1680597579000,"category_descrip":"","create_by":"57","category_title":"合作单位","category_path":"/hezuodanwei","category_keyword":"","id":21,"update_by":"57","create_date":1625903855000},{"category_display":"enable","category_flag":"f","top_id":0,"category_type":"1","del":0,"leaf":1,"category_pinyin":"huandenglanmu","category_sort":0,"update_date":1679393057000,"create_by":"57","category_title":"幻灯栏目","category_path":"/huandenglanmu","id":99,"update_by":"57","create_date":1679393057000}]